{"ab": 0.5837, "ace": 0.0, "af": 0.0, "am": 0.7379, "an": 0.3307, "ann": 0.0096, "anp": 0.0, "ar": 0.9742, "ast": 0.4552, "ay": 0.0, "az": 0.2197, "azb": 0.4958, "ban": 0.0502, "be": 0.8148, "bew": 0.0188, "bg": 1.0, "bn": 0.2621, "bo": 0.0, "bqi": 1.0, "br": 0.6811, "brh": 0.1507, "bs": 0.8108, "ca": 0.9253, "cak": 0.5116, "ceb": 0.1809, "ckb": 0.3036, "co": 0.9983, "cs": 0.9987, "cy": 1.0, "da": 0.9983, "de": 1.0, "dsb": 1.0, "el": 1.0, "en-CA": 0.9983, "en-GB": 1.0, "eo": 0.9983, "es": 0.9983, "es-AR": 1.0, "es-CL": 1.0, "es-ES": 0.9983, "es-MX": 0.9983, "et": 0.5623, "eu": 1.0, "fa": 0.7654, "ff": 0.2787, "fi": 0.9983, "fr": 1.0, "fur": 1.0, "fy-NL": 1.0, "ga-IE": 0.2416, "gd": 0.8759, "gl": 1.0, "gn": 0.9991, "gu-IN": 0.2368, "he": 0.9991, "hi-IN": 0.3307, "hil": 0.0612, "hr": 0.9948, "hsb": 1.0, "hu": 1.0, "hus": 0.0, "hy-AM": 1.0, "ia": 1.0, "id": 0.917, "is": 0.9974, "it": 1.0, "ixl": 0.0, "ja": 0.9974, "jv": 0.0, "ka": 1.0, "kaa": 0.4242, "kab": 0.7899, "kk": 1.0, "km": 0.5679, "kmr": 0.6291, "kn": 0.2678, "ko": 1.0, "kw": 0.0153, "lij": 0.2612, "lo": 0.7248, "lt": 0.3871, "lv": 0.0, "meh": 0.5072, "mix": 0.0428, "ml": 0.8899, "mr": 0.2661, "ms": 0.0, "my": 0.3443, "nb-NO": 1.0, "ne-NP": 0.2114, "nl": 1.0, "nn-NO": 1.0, "nv": 0.0017, "oc": 0.8222, "om": 0.2071, "or": 0.1044, "pa-IN": 1.0, "pa-PK": 0.4198, "pai": 0.0, "pl": 0.9983, "ppl": 0.0144, "ps": 0.1747, "pt-BR": 1.0, "pt-PT": 1.0, "quc": 0.0, "quy": 0.0, "rm": 0.8969, "ro": 0.9983, "ru": 1.0, "sat": 0.8611, "sc": 0.8078, "scn": 0.7851, "si": 0.5579, "sk": 1.0, "skr": 0.5946, "sl": 0.9694, "sn": 0.0, "sq": 0.8799, "sr": 0.9983, "su": 0.5749, "sv-SE": 1.0, "szl": 0.28, "ta": 0.3023, "te": 0.3875, "tg": 1.0, "th": 0.9987, "tl": 0.685, "tok": 0.4172, "tr": 0.9991, "trs": 0.7291, "tsz": 0.0, "tt": 0.6051, "tzm": 0.1118, "ug": 0.9694, "uk": 0.9983, "ur": 0.3451, "uz": 0.4089, "vec": 0.2538, "vi": 0.9996, "wo": 0.0, "yo": 0.3971, "yua": 0.1603, "yue": 0.0, "zam": 0.0022, "zh-CN": 0.9983, "zh-HK": 0.0, "zh-TW": 1.0}