{"ab": 0, "ace": 0, "af": 0, "am": 99, "an": 50, "ann": 1, "anp": 0, "ar": 65, "ast": 62, "ay": 0, "az": 38, "azb": 60, "ban": 7, "be": 96, "bg": 100, "bn": 46, "bo": 0, "br": 90, "bs": 99, "ca": 90, "cak": 85, "ceb": 31, "ckb": 54, "co": 99, "cs": 100, "cy": 99, "da": 99, "de": 99, "dsb": 99, "el": 99, "en-CA": 100, "en-GB": 99, "eo": 96, "es": 99, "es-AR": 99, "es-CL": 99, "es-ES": 99, "es-MX": 79, "et": 74, "eu": 96, "fa": 78, "ff": 49, "fi": 98, "fr": 99, "fur": 99, "fy-NL": 99, "ga-IE": 38, "gd": 76, "gl": 100, "gn": 100, "gu-IN": 41, "he": 99, "hi-IN": 58, "hil": 9, "hr": 80, "hsb": 99, "hu": 99, "hus": 0, "hy-AM": 99, "ia": 99, "id": 80, "is": 99, "it": 99, "ixl": 0, "ja": 98, "jv": 0, "ka": 85, "kaa": 75, "kab": 92, "kk": 99, "kmr": 80, "kn": 46, "ko": 99, "kw": 2, "lij": 45, "lo": 78, "lt": 65, "meh": 0, "mix": 7, "ml": 45, "mr": 46, "ms": 0, "my": 60, "nb-NO": 99, "ne-NP": 36, "nl": 99, "nn-NO": 96, "nv": 0, "oc": 99, "or": 17, "pa-IN": 99, "pa-PK": 46, "pai": 0, "pl": 94, "ppl": 2, "pt-BR": 99, "pt-PT": 99, "quc": 0, "quy": 0, "rm": 99, "ro": 54, "ru": 99, "sat": 88, "sc": 81, "si": 90, "sk": 99, "skr": 100, "sl": 97, "sn": 0, "sq": 99, "sr": 82, "su": 82, "sv-SE": 99, "szl": 48, "ta": 52, "te": 62, "tg": 99, "th": 98, "tl": 67, "tok": 7, "tr": 99, "trs": 78, "tsz": 0, "tt": 64, "tzm": 20, "ug": 99, "uk": 99, "ur": 59, "uz": 73, "vec": 44, "vi": 99, "wo": 0, "yo": 70, "yua": 0, "zam": 0, "zh-CN": 99, "zh-HK": 0, "zh-TW": 99}