{"ach": 0.5548, "af": 0.3715, "an": 0.6562, "ar": 0.808, "ast": 0.5325, "az": 0.5631, "be": 1.0, "bg": 0.7706, "bn": 0.7032, "br": 0.9231, "bs": 0.5829, "ca": 0.8631, "ca-valencia": 0.7467, "cak": 0.8878, "cs": 0.9984, "cy": 1.0, "da": 1.0, "de": 1.0, "dsb": 1.0, "el": 1.0, "en-CA": 0.9485, "en-GB": 1.0, "eo": 1.0, "es-AR": 1.0, "es-CL": 1.0, "es-ES": 1.0, "es-MX": 0.9137, "et": 0.8464, "eu": 0.9695, "fa": 0.7477, "ff": 0.5882, "fi": 0.9867, "fr": 0.9957, "fur": 1.0, "fy-NL": 1.0, "ga-IE": 0.5263, "gd": 0.9098, "gl": 0.9735, "gn": 0.9977, "gu-IN": 0.597, "he": 0.9364, "hi-IN": 0.6758, "hr": 0.821, "hsb": 1.0, "hu": 1.0, "hy-AM": 0.8116, "ia": 0.9987, "id": 0.9271, "is": 0.9245, "it": 1.0, "ja": 0.9998, "ja-JP-mac": 0.9998, "ka": 0.9785, "kab": 0.9489, "kk": 1.0, "km": 0.5211, "kn": 0.4899, "ko": 1.0, "lij": 0.6338, "lt": 0.8503, "lv": 0.5784, "mk": 0.4536, "mr": 0.6087, "ms": 0.5682, "my": 0.488, "nb-NO": 0.9991, "ne-NP": 0.5105, "nl": 1.0, "nn-NO": 0.9743, "oc": 0.9597, "pa-IN": 0.8827, "pl": 0.9909, "pt-BR": 1.0, "pt-PT": 1.0, "rm": 0.9955, "ro": 0.7926, "ru": 1.0, "sat": 0.9399, "sc": 0.8021, "sco": 0.6443, "si": 0.7469, "sk": 1.0, "sl": 0.9804, "son": 0.438, "sq": 0.9869, "sr": 0.9229, "sv-SE": 1.0, "szl": 0.6532, "ta": 0.5273, "te": 0.6356, "tg": 0.9877, "th": 0.9945, "tl": 0.7869, "tr": 0.9986, "trs": 0.5598, "uk": 1.0, "ur": 0.6925, "uz": 0.5238, "vi": 0.9826, "xh": 0.3886, "zh-CN": 1.0, "zh-TW": 1.0}