{"ach": 0.7939, "af": 0.5393, "an": 0.8217, "ar": 0.8865, "ast": 0.7274, "az": 0.8216, "be": 1.0, "bg": 0.9043, "bn": 0.9581, "br": 0.9837, "bs": 0.7967, "ca": 0.9187, "ca-valencia": 0.9037, "cak": 0.9962, "cs": 0.9714, "cy": 1.0, "da": 1.0, "de": 1.0, "dsb": 1.0, "el": 0.9574, "en-CA": 1.0, "en-GB": 1.0, "eo": 0.9954, "es-AR": 1.0, "es-CL": 1.0, "es-ES": 1.0, "es-MX": 1.0, "et": 0.9692, "eu": 1.0, "fa": 0.8758, "ff": 0.8139, "fi": 1.0, "fr": 1.0, "fy-NL": 1.0, "ga-IE": 0.7505, "gd": 0.9092, "gl": 0.8209, "gn": 1.0, "gu-IN": 0.8786, "he": 0.9495, "hi-IN": 0.9102, "hr": 0.9825, "hsb": 1.0, "hu": 1.0, "hy-AM": 0.9912, "ia": 1.0, "id": 0.9969, "is": 0.8745, "it": 1.0, "ja": 1.0, "ja-JP-mac": 1.0, "ka": 1.0, "kab": 1.0, "kk": 0.9876, "km": 0.6941, "kn": 0.7199, "ko": 0.9997, "lij": 0.8698, "lt": 0.9999, "lv": 0.8297, "mk": 0.5052, "mr": 0.8877, "ms": 0.8331, "my": 0.6857, "nb-NO": 1.0, "ne-NP": 0.7019, "nl": 1.0, "nn-NO": 1.0, "oc": 1.0, "pa-IN": 0.832, "pl": 1.0, "pt-BR": 1.0, "pt-PT": 0.9997, "rm": 0.9973, "ro": 1.0, "ru": 0.9978, "si": 0.6746, "sk": 0.9682, "sl": 0.9959, "son": 0.6462, "sq": 0.9833, "sr": 0.9654, "sv-SE": 1.0, "ta": 0.7665, "te": 0.8124, "th": 0.9948, "tl": 0.9931, "tr": 0.9981, "trs": 0.7918, "uk": 0.9997, "ur": 0.9169, "uz": 0.7251, "vi": 0.9743, "xh": 0.581, "zh-CN": 1.0, "zh-TW": 1.0}